[
  {
    "_id": 119,
    "firstname": "Bertha",
    "lastname": "Evans",
    "grade": 75
  },
  {
    "_id": 126,
    "firstname": "Bridgett",
    "lastname": "Potts",
    "grade": 92
  },
  {
    "_id": 118,
    "firstname": "Le",
    "lastname": "Bauer",
    "grade": 33
  },
  {
    "_id": 122,
    "firstname": "Antoinette",
    "lastname": "Kemp",
    "grade": 53
  },
  {
    "_id": 129,
    "firstname": "Mcclure",
    "lastname": null,
    "grade": 67
  },
  {
    "_id": 118,
    "firstname": null,
    "lastname": null,
    "grade": 90
  },
  {
    "_id": 122,
    "firstname": "Karin",
    "lastname": "Bartlett",
    "grade": 85
  }
]